{"cameraMode":{"drawMode":0,"name":"Shaded","section":"Shading Mode"},"sceneLighting":false,"audioPlay":false,"sceneViewState":{"showFog":true,"showMaterialUpdate":false,"showSkybox":false,"showFlares":true,"showImageEffects":true,"showParticleSystems":true},"in2DMode":false,"pivot":{"x":465.08880615234377,"y":7.084303855895996,"z":-72.98773956298828},"rotation":{"x":0.26296451687812807,"y":0.6679844260215759,"z":-0.2745782732963562,"w":0.6397314667701721},"size":28.238447189331056,"orthographic":false}