{"cameraMode":{"drawMode":0,"name":"Shaded","section":"Shading Mode"},"sceneLighting":false,"audioPlay":false,"sceneViewState":{"showFog":true,"showMaterialUpdate":false,"showSkybox":false,"showFlares":true,"showImageEffects":true,"showParticleSystems":true},"in2DMode":false,"pivot":{"x":-62.91999816894531,"y":2.130000114440918,"z":-6.889999866485596},"rotation":{"x":-0.30103522539138796,"y":0.03631100058555603,"z":-0.011484963819384575,"w":-0.9528784155845642},"size":2.7990384101867677,"orthographic":false}